{
  "components": [
    {
      "data": {
        "contents_checksum": "98e88208b2a820b75a656849a5c868aad62ba1e174ac768867d4fc1a5f6ffb5c", 
        "source": "", 
        "type": "tar"
      }, 
      "dependencies": [
        "core", 
        "gsutil-nix", 
        "gsutil-win"
      ], 
      "details": {
        "description": "Provides the gsutil tool for interacting with Google Cloud Storage.", 
        "display_name": "Cloud Storage Command Line Tool"
      }, 
      "id": "gsutil", 
      "is_configuration": false, 
      "is_hidden": false, 
      "is_required": false, 
      "platform": {}, 
      "version": {
        "build_number": 20190621160142, 
        "version_string": "4.39"
      }
    }
  ], 
  "revision": 20190628151358, 
  "schema_version": {
    "no_update": false, 
    "url": "https://dl.google.com/dl/cloudsdk/channels/rapid/google-cloud-sdk.tar.gz", 
    "version": 3
  }, 
  "version": "253.0.0"
}